front_matter_parser/__init__.py
front_matter_parser/index.py
front_matter_parser/worker.py
front_matter_parser_py-0.0.1.dist-info/LICENSE
front_matter_parser_py-0.0.1.dist-info/WHEEL
front_matter_parser_py-0.0.1.dist-info/METADATA
front_matter_parser_py-0.0.1.dist-info/RECORD
